blm/__init__.py
blm/blm_cluster.py
blm/lib/__init__.py
blm/lib/blm_batch.py
blm/lib/blm_concat.py
blm/lib/blm_results.py
blm/lib/blm_setup.py
blm/lib/fileio.py
test/__init__.py
test/blm_cluster_test.py
test/cleanup.py
test/generate_test_data.py
pyblm-0.1.3.dist-info/METADATA
pyblm-0.1.3.dist-info/WHEEL
pyblm-0.1.3.dist-info/entry_points.txt
pyblm-0.1.3.dist-info/top_level.txt
pyblm-0.1.3.dist-info/RECORD
