Metadata-Version: 2.1
Name: pyblm
Version: 0.1.3
Summary: The Big Linear Models Toolbox
Home-page: https://github.com/tommaullin/blm
Author: Tom Maullin
Author-email: TomMaullin@gmail.com
License: UNKNOWN
Platform: UNKNOWN
Classifier: Programming Language :: Python :: 3
Classifier: License :: OSI Approved :: MIT License
Classifier: Operating System :: OS Independent
Requires-Python: >=3.6
Requires-Dist: bokeh (==2.4.3)
Requires-Dist: dask (>=2023.3.2)
Requires-Dist: dask-jobqueue (>=0.8.1)
Requires-Dist: distributed (>=2023.3.2)
Requires-Dist: nibabel (>=4.0.2)
Requires-Dist: nilearn (>=0.9.2)
Requires-Dist: numpy (>=1.23.4)
Requires-Dist: pandas (>=1.5.1)
Requires-Dist: PyYAML (>=6.0)
Requires-Dist: scipy (>=1.9.3)
